<!DOCTYPE suite SYSTEM "http://testng.org/testng-1.0.dtd">
<suite name="Payroll Suite NIDirector AtoD_Month6">
<test name="1">
    <classes>
        <class name="com.test.xcdhr.Salesforce_Core_Framework1.hrms_payroll.NIDirector_AtoDMonth6" ></class>  
    </classes>
</test>
<test name="2">
    <classes>
        <class name="com.test.xcdhr.Salesforce_Core_Framework1.hrms_payroll.ProcessPayrollForNI_AtoD" ></class>  
    </classes>
</test>
<test name="3">
    <classes>
        <class name="com.test.xcdhr.Salesforce_Core_Framework1.hrms_payroll.TestReports" ></class>  
    </classes>
</test>
</suite>